quantsc
