Metadata-Version: 1.0
Name: quantsc
Version: 1.0.1.2
Summary: A Quantitative Finance Library
Home-page: https://quantsc.org/
Author: Yuanhao Lu, Jonathan Qin, Aditya Prasad 
Author-email: terryl@usc.edu
License: MIT
Platform: UNKNOWN
